CHANGELOG.txt
LICENCE.txt
MANIFEST.in
README.txt
setup.py
CalculadoraCla/__init__.py
CalculadoraCla/pytransform/__init__.py
CalculadoraClasesss.egg-info/PKG-INFO
CalculadoraClasesss.egg-info/SOURCES.txt
CalculadoraClasesss.egg-info/dependency_links.txt
CalculadoraClasesss.egg-info/top_level.txt