Metadata-Version: 1.1
Name: CalculadoraClasesss
Version: 0.5.4
Summary: Operaciones de 2 digitos con Interfaz
Home-page: UNKNOWN
Author: Wilbert Sanchez
Author-email: wilbertenrique@gmail.com
License: MIT
Keywords: calculator
Platform: UNKNOWN
Classifier: Development Status :: 5 - Production/Stable
Classifier: Intended Audience :: Education
Classifier: Operating System :: Microsoft :: Windows :: Windows 10
Classifier: License :: OSI Approved :: MIT License
Classifier: Programming Language :: Python :: 3
